stopwatch/__init__.py
stopwatch/stopwatch.py
py_stopwatch-0.2.2.dist-info/AUTHORS.rst
py_stopwatch-0.2.2.dist-info/LICENSE
py_stopwatch-0.2.2.dist-info/METADATA
py_stopwatch-0.2.2.dist-info/WHEEL
py_stopwatch-0.2.2.dist-info/top_level.txt
py_stopwatch-0.2.2.dist-info/RECORD
