Metadata-Version: 2.1
Name: py-stopwatch
Version: 0.2.2
Summary: Stopwatch class for timing portions of python code
Home-page: https://github.com/hrishikeshrt/py_stopwatch
Author: Hrishikesh Terdalkar
Author-email: hrishikeshrt@linuxmail.org
License: MIT license
Keywords: stopwatch
Classifier: Development Status :: 3 - Alpha
Classifier: License :: OSI Approved :: MIT License
Classifier: Natural Language :: English
Classifier: Programming Language :: Python :: 3
Classifier: Programming Language :: Python :: 3.6
Classifier: Programming Language :: Python :: 3.7
Classifier: Programming Language :: Python :: 3.8
Classifier: Programming Language :: Python :: 3.9
Requires-Python: >=3.6
License-File: LICENSE
License-File: AUTHORS.rst
